simulating/__init__.py
simulating/conditions/__init__.py
simulating/conditions/condition.py
simulating/conditions/does_not_occur_before_condition.py
simulating/conditions/occurs_before_condition.py
simulating/conditions/occurs_before_condition_with_cycles.py
simulating/conditions/sync_condition.py
simulating/log/__init__.py
simulating/log/event_log.py
simulating/log/export.py
simulating/systems/__init__.py
simulating/systems/deadlock_exception.py
simulating/systems/firing.py
simulating/systems/multi_agent_system.py
multi_agent_systems-1.0.0.dist-info/LICENSE
multi_agent_systems-1.0.0.dist-info/METADATA
multi_agent_systems-1.0.0.dist-info/WHEEL
multi_agent_systems-1.0.0.dist-info/top_level.txt
multi_agent_systems-1.0.0.dist-info/RECORD
