Metadata-Version: 2.1
Name: multi-agent-systems
Version: 1.0.0
Summary: Module for simulating multi-agent-systems using Petri nets from pm4py
Home-page: https://github.com/haleen24/MultiAgentSystems.git
Author: haleen24
Author-email: 
Project-URL: Documentation, https://github.com/haleen24/MultiAgentSystems.git
Keywords: multi-agent-systems simulating
Classifier: Programming Language :: Python :: 3.11
Classifier: License :: OSI Approved :: MIT License
Classifier: Operating System :: OS Independent
Requires-Python: >=3.7
License-File: LICENSE
Requires-Dist: requests >=2.25.1
